{"GlobalPropertiesHash":"IY/RvloqkLWLe6mcEblgHu/B1SRXyCi24RZN/smCsLU=","FingerprintPatternsHash":"gq3WsqcKBUGTSNle7RKKyXRIwh7M8ccEqOqYvIzoM04=","PropertyOverridesHash":"8ZRc1sGeVrPBx4lD717BgRaQekyh78QKV9SKsdt638U=","InputHashes":["C0JhGY7YQTtJBO\u002BTLfVLj\u002BNnalGl3\u002BcAthod\u002BN56XVo=","8d8vVyAntPHAyc/GS04atBkm46DujjGlrFKpW0\u002Bh3kk=","NNUquLnXWll/Z1ecJpUU7MWicEwXP3HR9SeYlt65jf8=","n4kKjH9ZrYPE9xpmPiae0vERxsSDuCV/rCwsCGBMeAo=","rfukTGX\u002Bo4SJjF08sABBq7ietD8NBPtwx7JxInKIA38=","8hmpGKQfBHTl2EH5rTflf1CecVlnCHHHp8CmOD9xBQQ="],"CachedAssets":{"8d8vVyAntPHAyc/GS04atBkm46DujjGlrFKpW0\u002Bh3kk=":{"Identity":"C:\\Users\\Asus\\Smart-Course-Management-Portal\\SmartCourseManagement.API\\wwwroot\\css\\style.css","SourceId":"SmartCourseManagement.API","SourceType":"Discovered","ContentRoot":"C:\\Users\\Asus\\Smart-Course-Management-Portal\\SmartCourseManagement.API\\wwwroot\\","BasePath":"/","RelativePath":"css/style#[.{fingerprint}]?.css","AssetKind":"All","AssetMode":"All","AssetRole":"Primary","AssetMergeBehavior":null,"AssetMergeSource":"","RelatedAsset":null,"AssetTraitName":null,"AssetTraitValue":null,"Fingerprint":"agxjyy8qee","Integrity":"5qVvurhanPO0bKDN7DBUs1pafskArvCam5WLl4BMwUc=","CopyToOutputDirectory":"Never","CopyToPublishDirectory":"PreserveNewest","OriginalItemSpec":"wwwroot\\css\\style.css","FileLength":4105,"LastWriteTime":"2026-03-23T07:35:43.7135112+00:00"},"NNUquLnXWll/Z1ecJpUU7MWicEwXP3HR9SeYlt65jf8=":{"Identity":"C:\\Users\\Asus\\Smart-Course-Management-Portal\\SmartCourseManagement.API\\wwwroot\\index.html","SourceId":"SmartCourseManagement.API","SourceType":"Discovered","ContentRoot":"C:\\Users\\Asus\\Smart-Course-Management-Portal\\SmartCourseManagement.API\\wwwroot\\","BasePath":"/","RelativePath":"index#[.{fingerprint}]?.html","AssetKind":"All","AssetMode":"All","AssetRole":"Primary","AssetMergeBehavior":null,"AssetMergeSource":"","RelatedAsset":null,"AssetTraitName":null,"AssetTraitValue":null,"Fingerprint":"cpzrbltasd","Integrity":"gJzAW52fbP0rDvEi0OuJEzZQHCDz5oz6c1u5XH6B\u002BsQ=","CopyToOutputDirectory":"Never","CopyToPublishDirectory":"PreserveNewest","OriginalItemSpec":"wwwroot\\index.html","FileLength":5635,"LastWriteTime":"2026-03-23T07:34:51.7287885+00:00"},"n4kKjH9ZrYPE9xpmPiae0vERxsSDuCV/rCwsCGBMeAo=":{"Identity":"C:\\Users\\Asus\\Smart-Course-Management-Portal\\SmartCourseManagement.API\\wwwroot\\js\\app.js","SourceId":"SmartCourseManagement.API","SourceType":"Discovered","ContentRoot":"C:\\Users\\Asus\\Smart-Course-Management-Portal\\SmartCourseManagement.API\\wwwroot\\","BasePath":"/","RelativePath":"js/app#[.{fingerprint}]?.js","AssetKind":"All","AssetMode":"All","AssetRole":"Primary","AssetMergeBehavior":null,"AssetMergeSource":"","RelatedAsset":null,"AssetTraitName":null,"AssetTraitValue":null,"Fingerprint":"vxgkxkldxr","Integrity":"w7OjOMrtRM4Jj\u002B17/7zNmLikNjfBPyrHlS7NfxDgwtE=","CopyToOutputDirectory":"Never","CopyToPublishDirectory":"PreserveNewest","OriginalItemSpec":"wwwroot\\js\\app.js","FileLength":6523,"LastWriteTime":"2026-03-23T07:35:07.1024303+00:00"},"C0JhGY7YQTtJBO\u002BTLfVLj\u002BNnalGl3\u002BcAthod\u002BN56XVo=":{"Identity":"C:\\Users\\Asus\\Smart-Course-Management-Portal\\SmartCourseManagement.API\\wwwroot\\assets\\university_bg.png","SourceId":"SmartCourseManagement.API","SourceType":"Discovered","ContentRoot":"C:\\Users\\Asus\\Smart-Course-Management-Portal\\SmartCourseManagement.API\\wwwroot\\","BasePath":"/","RelativePath":"assets/university_bg#[.{fingerprint}]?.png","AssetKind":"All","AssetMode":"All","AssetRole":"Primary","AssetMergeBehavior":null,"AssetMergeSource":"","RelatedAsset":null,"AssetTraitName":null,"AssetTraitValue":null,"Fingerprint":"uewl7u4gbj","Integrity":"qok2\u002BQv3X1WHjXAEeXyPvsDt\u002BcSpHPlp0Fj0\u002B5ZH1Ds=","CopyToOutputDirectory":"Never","CopyToPublishDirectory":"PreserveNewest","OriginalItemSpec":"wwwroot\\assets\\university_bg.png","FileLength":72049,"LastWriteTime":"2026-03-23T07:49:04.966526+00:00"}},"CachedCopyCandidates":{}}